{
  "Field": "Πεδίο",
  "GPBoolean": "Boolean",
  "GPComposite": "π_Composite___________________Ω",
  "GPDataFile": "Αρχείο δεδομένων",
  "GPDate": "Ημερομηνία",
  "GPDouble": "Κινητής υποδιαστολής διπλής ακρίβειας",
  "GPFeatureRecordSetLayer": "Εγγραφή στοιχείου",
  "GPLinearUnit": "Γραμμική μονάδα",
  "GPLong": "Μακρύ",
  "GPMultiValue:Field": "Πεδίο πολλαπλών τιμών",
  "GPMultiValue:GPBoolean": "π_Multi-value Boolean____________________Ω",
  "GPMultiValue:GPComposite": "π_Multi-value Composite______________________Ω",
  "GPMultiValue:GPDataFile": "π_Multi-value Data File______________________Ω",
  "GPMultiValue:GPDate": "π_Multi-value Date_________________Ω",
  "GPMultiValue:GPDouble": "π_Multi-value Double___________________Ω",
  "GPMultiValue:GPFeatureRecordSetLayer": "π_Multi-value Feature Record Set Layer___________________Ω",
  "GPMultiValue:GPLinearUnit": "π_Multi-value Linear Unit________________________Ω",
  "GPMultiValue:GPLong": "π_Multi-value Long_________________Ω",
  "GPMultiValue:GPRasterDataLayer": "π_Multi-value Raster Layer_________________________Ω",
  "GPMultiValue:GPRecordSet": "π_Multi-value Record Set_______________________Ω",
  "GPMultiValue:GPString": "Συμβολοσειρά πολλαπλών τιμών",
  "GPMultiValue:GPValueTable": "π_Multi-value Value Table________________________Ω",
  "GPRasterDataLayer": "Θεματικό επίπεδο raster",
  "GPRecordSet": "Σύνολο εγγραφών",
  "GPString": "Συμβολοσειρά",
  "GPValueTable": "Πίνακας τιμών",
  "gpSelection": "Επιλογή τύπου GP",
  "gpTypes": "Τύποι GP"
}
