{
  "Field": "שדה",
  "GPBoolean": "בוליאני",
  "GPComposite": "כן_Composite___________________ש",
  "GPDataFile": "קובץ נתונים",
  "GPDate": "תאריך",
  "GPDouble": "כפול",
  "GPFeatureRecordSetLayer": "רשומת ישות",
  "GPLinearUnit": "יחידה לינארית",
  "GPLong": "ארוך",
  "GPMultiValue:Field": "שדה מרובה ערכים",
  "GPMultiValue:GPBoolean": "כן_Multi-value Boolean____________________ש",
  "GPMultiValue:GPComposite": "כן_Multi-value Composite______________________ש",
  "GPMultiValue:GPDataFile": "כן_Multi-value Data File______________________ש",
  "GPMultiValue:GPDate": "כן_Multi-value Date_________________ש",
  "GPMultiValue:GPDouble": "כן_Multi-value Double___________________ש",
  "GPMultiValue:GPFeatureRecordSetLayer": "כן_Multi-value Feature Record Set Layer___________________ש",
  "GPMultiValue:GPLinearUnit": "כן_Multi-value Linear Unit________________________ש",
  "GPMultiValue:GPLong": "כן_Multi-value Long_________________ש",
  "GPMultiValue:GPRasterDataLayer": "כן_Multi-value Raster Layer_________________________ש",
  "GPMultiValue:GPRecordSet": "כן_Multi-value Record Set_______________________ש",
  "GPMultiValue:GPString": "מחרוזת מרובת ערכים",
  "GPMultiValue:GPValueTable": "כן_Multi-value Value Table________________________ש",
  "GPRasterDataLayer": "שכבת רסטר",
  "GPRecordSet": "סט רשומות",
  "GPString": "מחרוזת",
  "GPValueTable": "טבלת ערכים",
  "gpSelection": "בחירת סוג GP",
  "gpTypes": "סוגי GP"
}
